<?xml version="1.0" encoding="utf-8" ?>
<dwsync>
<file name="bootstrap.min.js" server="smartvalley.lk/public_html/" local="131320542390000000" remote="131908428000000000" Dst="0" />
<file name="contact-form.js" server="smartvalley.lk/public_html/" local="131534915830000000" remote="131908428000000000" Dst="0" />
<file name="jquery.ajaxchimp.min.js" server="smartvalley.lk/public_html/" local="131320542430000000" remote="131908428000000000" Dst="0" />
<file name="jquery.countdown.min.js" server="smartvalley.lk/public_html/" local="131320542440000000" remote="131908428000000000" Dst="0" />
<file name="jquery.gradientify.min.js" server="smartvalley.lk/public_html/" local="131320542440000000" remote="131908428000000000" Dst="0" />
<file name="newsletter-form.js" server="smartvalley.lk/public_html/" local="131554918740000000" remote="131908428600000000" Dst="0" />
<file name="jquery1.11.2.min.js" server="smartvalley.lk/public_html/" local="131320542600000000" remote="131908428600000000" Dst="0" />
<file name="prefixfree.min.js" server="smartvalley.lk/public_html/" local="131320542550000000" remote="131908428600000000" Dst="0" />
<file name="scrollreveal.min.js" server="smartvalley.lk/public_html/" local="131320542590000000" remote="131908428600000000" Dst="0" />
</dwsync>